wagtailphotovoter/__init__.py
wagtailphotovoter/admin.py
wagtailphotovoter/apps.py
wagtailphotovoter/forms.py
wagtailphotovoter/models.py
wagtailphotovoter/tests.py
wagtailphotovoter/views.py
wagtailphotovoter/wagtail_hooks.py
wagtailphotovoter/migrations/0001_initial.py
wagtailphotovoter/migrations/0002_auto_20200215_1416.py
wagtailphotovoter/migrations/0003_votes_comments.py
wagtailphotovoter/migrations/0004_auto_20200303_2134.py
wagtailphotovoter/migrations/0005_auto_20200304_2259.py
wagtailphotovoter/migrations/0006_historicalvotes.py
wagtailphotovoter/migrations/0007_auto_20210224_2256.py
wagtailphotovoter/migrations/0008_alter_historicalvotes_options_competition_votinghelp_and_more.py
wagtailphotovoter/migrations/__init__.py
wagtailphotovoter/static/lightbox/css/lightbox.css
wagtailphotovoter/static/lightbox/images/close.png
wagtailphotovoter/static/lightbox/images/loading.gif
wagtailphotovoter/static/lightbox/images/next.png
wagtailphotovoter/static/lightbox/images/prev.png
wagtailphotovoter/static/lightbox/js/lightbox.js
wagtailphotovoter/templates/wagtailphotovoter/add.html
wagtailphotovoter/templates/wagtailphotovoter/image_choice.html
wagtailphotovoter/templates/wagtailphotovoter/result.html
wagtailphotovoter/templates/wagtailphotovoter/vote.html
wagtail_photo_voter-0.10.3.dist-info/LICENSE
wagtail_photo_voter-0.10.3.dist-info/METADATA
wagtail_photo_voter-0.10.3.dist-info/WHEEL
wagtail_photo_voter-0.10.3.dist-info/top_level.txt
wagtail_photo_voter-0.10.3.dist-info/RECORD
