Metadata-Version: 2.1
Name: wagtail-photo-voter
Version: 0.10.3
Summary: A Wagtail module for creating Photo competitions with voting
Home-page: https://github.com/straend/wagtail_photo_voter
Author: Tomas Strand
Author-email: wagtail@tomas.fik1.net
Classifier: Programming Language :: Python :: 3
Classifier: License :: OSI Approved :: MIT License
Classifier: Operating System :: OS Independent
Classifier: Framework :: Django
Classifier: Framework :: Wagtail
Requires-Python: >=3.8
License-File: LICENSE
Requires-Dist: Django (>=4.1)
Requires-Dist: wagtail (>=4.1)
Requires-Dist: django-bootstrap4
Requires-Dist: django-exiffield
